mqttasgi/__init__.py
mqttasgi/cli.py
mqttasgi/consumers.py
mqttasgi/server.py
mqttasgi/testing.py
mqttasgi/utils.py
mqttasgi-0.2.0.dist-info/METADATA
mqttasgi-0.2.0.dist-info/RECORD
mqttasgi-0.2.0.dist-info/WHEEL
mqttasgi-0.2.0.dist-info/entry_points.txt
mqttasgi-0.2.0.dist-info/top_level.txt
